filepaths/__init__.py
filepaths-0.0.8.dist-info/LICENSE
filepaths-0.0.8.dist-info/METADATA
filepaths-0.0.8.dist-info/WHEEL
filepaths-0.0.8.dist-info/top_level.txt
filepaths-0.0.8.dist-info/RECORD
