Metadata-Version: 2.1
Name: filepaths
Version: 0.0.8
Summary: Root-agnostic filepath generation
Home-page: https://github.com/hfeiss/filepaths
Author: Hunter Feiss
Author-email: hfeiss@gmail.com
License: MIT
Keywords: filepath files directories
Platform: UNKNOWN
Classifier: Programming Language :: Python :: 3
Classifier: License :: OSI Approved :: MIT License
Classifier: Operating System :: OS Independent
Requires-Python: >=3
Requires-Dist: addict
